mergify_cli/__init__.py
mergify_cli/_globals.py
mergify_cli/cli.py
mergify_cli/github_types.py
mergify_cli/utils.py
mergify_cli/ci/__init__.py
mergify_cli/ci/cli.py
mergify_cli/ci/detector.py
mergify_cli/ci/git_refs/__init__.py
mergify_cli/ci/git_refs/detector.py
mergify_cli/ci/junit_processing/__init__.py
mergify_cli/ci/junit_processing/cli.py
mergify_cli/ci/junit_processing/junit.py
mergify_cli/ci/junit_processing/quarantine.py
mergify_cli/ci/junit_processing/upload.py
mergify_cli/ci/scopes/__init__.py
mergify_cli/ci/scopes/changed_files.py
mergify_cli/ci/scopes/cli.py
mergify_cli/ci/scopes/exceptions.py
mergify_cli/ci/scopes/config/__init__.py
mergify_cli/ci/scopes/config/root.py
mergify_cli/ci/scopes/config/scopes.py
mergify_cli/stack/__init__.py
mergify_cli/stack/changes.py
mergify_cli/stack/checkout.py
mergify_cli/stack/cli.py
mergify_cli/stack/edit.py
mergify_cli/stack/github_action_auto_rebase.py
mergify_cli/stack/push.py
mergify_cli/stack/setup.py
mergify_cli/stack/hooks/commit-msg
mergify_cli/stack/hooks/prepare-commit-msg
mergify_cli/tests/__init__.py
mergify_cli/tests/conftest.py
mergify_cli/tests/test_utils.py
mergify_cli/tests/utils.py
mergify_cli/tests/ci/__init__.py
mergify_cli/tests/ci/junit_example.xml
mergify_cli/tests/ci/pull_request.json
mergify_cli/tests/ci/report.xml
mergify_cli/tests/ci/test_cli.py
mergify_cli/tests/ci/test_detector.py
mergify_cli/tests/ci/test_junit.py
mergify_cli/tests/ci/git_refs/test_git_refs_detector.py
mergify_cli/tests/ci/junit_processing/__init__.py
mergify_cli/tests/ci/junit_processing/test_check_failing_spans.py
mergify_cli/tests/ci/junit_processing/test_cli.py
mergify_cli/tests/ci/junit_processing/test_upload.py
mergify_cli/tests/ci/scopes/__init__.py
mergify_cli/tests/ci/scopes/test_changed_files.py
mergify_cli/tests/ci/scopes/test_cli.py
mergify_cli/tests/stack/__init__.py
mergify_cli/tests/stack/test_push.py
mergify_cli/tests/stack/test_setup.py
mergify_cli-2026.1.14.1.dist-info/METADATA
mergify_cli-2026.1.14.1.dist-info/WHEEL
mergify_cli-2026.1.14.1.dist-info/entry_points.txt
mergify_cli-2026.1.14.1.dist-info/licenses/LICENSE
mergify_cli-2026.1.14.1.dist-info/RECORD
