Metadata-Version: 2.4
Name: mergify_cli
Version: 2026.1.14.1
Summary: Mergify CLI is a tool that automates the creation and management of stacked pull requests on GitHub
Author-email: Mehdi Abaakouk <sileht@mergify.com>
License-Expression: Apache-2.0
License-File: LICENSE
Requires-Python: >=3.13
Requires-Dist: aiofiles==25.1.0
Requires-Dist: click-default-group==1.2.4
Requires-Dist: click==8.3.1
Requires-Dist: httpx==0.28.1
Requires-Dist: opentelemetry-exporter-otlp-proto-http==1.39.1
Requires-Dist: opentelemetry-sdk==1.39.1
Requires-Dist: pydantic==2.12.5
Requires-Dist: pyyaml==6.0.3
Requires-Dist: rich==14.2.0
Requires-Dist: tenacity==9.1.2
